<?xml version="1.0"?>
<Results version="1.0">
<ReportNode type="testrun">
<ReportNode type="Iteration">
<ReportNode type="Action">
<ReportNode type="Transaction">
<Data>
    <Name>Tran1</Name>
    <Description>Transaction "Tran1" started.</Description>
    <StartTime>2022-03-30 12:27:15</StartTime>
    <Result>Done</Result>
    <Extension>
      <IconKey>c61bd884f05f49bf88360eaea4681cd3</IconKey>
      <IsPlainTextNodeName>True</IsPlainTextNodeName>
      <NodeType>Start Transaction</NodeType>
    </Extension>
  </Data>
</ReportNode>
<ReportNode type="Transaction">
<Data>
    <Name>Tran1</Name>
    <Description>Transaction "Tran1" ended with "Pass" status (Total Duration: 5.8427 sec).</Description>
    <StartTime>2022-03-30 12:27:21</StartTime>
    <Result>Done</Result>
    <Extension>
      <IconKey>e0a71dc2524d4f77bc696e80ac1e2806</IconKey>
      <IsPlainTextNodeName>True</IsPlainTextNodeName>
      <NodeType>End Transaction</NodeType>
    </Extension>
  </Data>
</ReportNode>
<Data>
    <Name>Action1</Name>
    <Description />
    <StartTime>2022-03-30 12:27:15</StartTime>
    <Duration>6</Duration>
    <Result>Done</Result>
    <InputParameters />
    <Extension>
      <IconKey>caec4a4abf0b4ce8a985295eac3adc6e</IconKey>
      <IsPlainTextNodeName>True</IsPlainTextNodeName>
    </Extension>
  </Data>
</ReportNode>
<ReportNode type="Action">
<Data>
    <Name>Action2</Name>
    <Description />
    <StartTime>2022-03-30 12:27:21</StartTime>
    <Result>Done</Result>
    <InputParameters />
    <Extension>
      <IconKey>caec4a4abf0b4ce8a985295eac3adc6e</IconKey>
      <IsPlainTextNodeName>True</IsPlainTextNodeName>
    </Extension>
  </Data>
</ReportNode>
<ReportNode type="Action">
<Data>
    <Name>Action3</Name>
    <Description />
    <StartTime>2022-03-30 12:27:22</StartTime>
    <Result>Done</Result>
    <InputParameters />
    <Extension>
      <IconKey>caec4a4abf0b4ce8a985295eac3adc6e</IconKey>
      <IsPlainTextNodeName>True</IsPlainTextNodeName>
    </Extension>
  </Data>
</ReportNode>
<ReportNode type="Action">
<Data>
    <Name>Action4</Name>
    <Description />
    <StartTime>2022-03-30 12:27:22</StartTime>
    <Result>Done</Result>
    <InputParameters />
    <Extension>
      <IconKey>caec4a4abf0b4ce8a985295eac3adc6e</IconKey>
      <IsPlainTextNodeName>True</IsPlainTextNodeName>
    </Extension>
  </Data>
</ReportNode>
<Data>
    <Name>Action0</Name>
    <Description />
    <StartTime>2022-03-30 12:27:15</StartTime>
    <Duration>7</Duration>
    <Result>Done</Result>
    <Extension>
      <IconKey>28441fb3ef454578b2c1571d21bc2f0d</IconKey>
      <IsPlainTextNodeName>True</IsPlainTextNodeName>
    </Extension>
    <Index>1</Index>
    <TestedApplications />
  </Data>
</ReportNode>
<Data>
    <Name>Driver</Name>
    <ToolName>Micro Focus UFT One</ToolName>
    <ToolVersion>2021</ToolVersion>
    <ToolVersionStringLiteral>2021</ToolVersionStringLiteral>
    <Description />
    <StartTime>2022-03-30 12:27:11</StartTime>
    <Duration>11</Duration>
    <Result>Done</Result>
    <InputParameters />
    <Extension>
      <IconKey>8af7ebef15ca4a24a9aca884e91a8e1d</IconKey>
      <IsPlainTextNodeName>True</IsPlainTextNodeName>
    </Extension>
    <Environment>
      <Timezone>00:00:00</Timezone>
      <Locale>English (United States)</Locale>
      <User>sfjbs</User>
      <CpuInfo>Intel(R) Xeon(R) CPU E5-2673 v4 @ 2.30GHz</CpuInfo>
      <NumberOfCores>2</NumberOfCores>
      <TotalMemory>8191</TotalMemory>
      <HostName>vm001</HostName>
      <OSInfo>Windows 10 20H2 (x64)</OSInfo>
    </Environment>
    <TestedApplications />
    <Links>
      <Link type="DataTable" reference="Default.xlsx" displayname="Default Data Table" />
    </Links>
  </Data>
</ReportNode>
<GeneralInfo>
    <ResultName>Res42</ResultName>
    <RunStartTime>2022-03-30 12:27:11</RunStartTime>
    <Timezone>00:00:00</Timezone>
    <OrchestrationToolName>Micro Focus UFT One</OrchestrationToolName>
    <OrchestrationToolVersion>2021</OrchestrationToolVersion>
    <OrchestrationToolVersionStringLiteral>2021</OrchestrationToolVersionStringLiteral>
  </GeneralInfo>
</Results>